CHANGELOG.txt
LICENSE.txt
MANIFEST.in
README.txt
ez_setup.py
setup.cfg
setup.py
ConfigConvert.egg-info/PKG-INFO
ConfigConvert.egg-info/SOURCES.txt
ConfigConvert.egg-info/dependency_links.txt
ConfigConvert.egg-info/entry_points.txt
ConfigConvert.egg-info/not-zip-safe
ConfigConvert.egg-info/requires.txt
ConfigConvert.egg-info/top_level.txt
configconvert/__init__.py
configconvert/internal.py
configconvert/service.py
doc/Makefile
doc/index.txt
doc/source/api.rst
doc/source/conf.py
doc/source/index.rst
doc/source/manual.rst
test/README.txt
test/doc.py
test/test.conf