Metadata-Version: 1.0
Name: ConfigConvert
Version: 0.2.0
Summary: Tools for managing config files. Built on ConversionKit.
Home-page: http://jimmyg.org/work/code/configconvert/index.html
Author: James Gardner
Author-email: UNKNOWN
License: GNU AGPLv3
Platform: UNKNOWN
Classifier: Development Status :: 3 - Alpha
Classifier: License :: OSI Approved :: GNU Affero General Public License v3
Classifier: Programming Language :: Python :: 2
Classifier: Topic :: Software Development :: Libraries :: Python Modules
Classifier: Environment :: Console
Classifier: Environment :: Web Environment
